opentsdb/__init__.py
opentsdb/exceptions.py
opentsdb/metrics.py
opentsdb/push_thread.py
opentsdb/tsdb_client.py
opentsdb/protocols/__init__.py
opentsdb/protocols/http_connect.py
opentsdb/protocols/telnet_connect.py
opentsdb/protocols/tsdb_connect.py
opentsdb/protocols/tests/__init__.py
opentsdb/protocols/tests/test_http_urls.py
opentsdb/tests/__init__.py
opentsdb/tests/conftest.py
opentsdb/tests/test_client.py
opentsdb/tests/test_metrics.py
opentsdb_client-0.6.1.dist-info/LICENSE
opentsdb_client-0.6.1.dist-info/METADATA
opentsdb_client-0.6.1.dist-info/WHEEL
opentsdb_client-0.6.1.dist-info/top_level.txt
opentsdb_client-0.6.1.dist-info/RECORD
