Metadata-Version: 2.1
Name: opentsdb-client
Version: 0.6.1
Summary: Python3 client for OpenTSDB
Home-page: https://github.com/neilbowman666/opentsdb-client
Author: Okeyja Teung
Author-email: dengyijian163@163.com
License: UNKNOWN
Download-URL: https://github.com/neilbowman666/opentsdb-client/archive/v0.6.1.zip
Keywords: opentsdb,tsdb,metrics
Platform: UNKNOWN
Classifier: Environment :: Console
Classifier: Intended Audience :: Developers
Classifier: License :: OSI Approved :: MIT License
Classifier: Natural Language :: English
Classifier: Operating System :: Microsoft :: Windows
Classifier: Operating System :: POSIX
Classifier: Programming Language :: Python :: 3.6
Classifier: Programming Language :: Python :: 3.5
Classifier: Programming Language :: Python :: 3 :: Only
License-File: LICENSE
Requires-Dist: setuptools
Requires-Dist: requests
